LICENSE
README.md
setup.cfg
setup.py
mVIRs/__init__.py
mVIRs/mvirs.py
mVIRs.egg-info/PKG-INFO
mVIRs.egg-info/SOURCES.txt
mVIRs.egg-info/dependency_links.txt
mVIRs.egg-info/entry_points.txt
mVIRs.egg-info/requires.txt
mVIRs.egg-info/top_level.txt