Metadata-Version: 2.1
Name: mVIRs
Version: 1.1.1
Summary: mVIRs: Localisation of inducible prophages using NGS data
Home-page: https://github.com/SushiLab/mVIRs
Download-URL: https://github.com/SushiLab/mVIRs/archive/refs/tags/1.1.1.tar.gz
Author: Hans-Joachim Ruscheweyh
Author-email: hansr@ethz.ch
License: GPLv3
Keywords: bioinformatics metagenomics NGS alignment OPRs Prophages
Platform: UNKNOWN
Classifier: Programming Language :: Python
Classifier: Programming Language :: Python :: 3
Classifier: Development Status :: 5 - Production/Stable
Classifier: Intended Audience :: Science/Research
Classifier: Topic :: Scientific/Engineering :: Bio-Informatics
Classifier: License :: OSI Approved :: GNU General Public License v3 (GPLv3)
Classifier: Operating System :: OS Independent
License-File: LICENSE
